markdown_checker/__init__.py
markdown_checker/markdown_link_base.py
markdown_checker/paths.py
markdown_checker/py.typed
markdown_checker/urls.py
markdown_checker/reports/__init__.py
markdown_checker/reports/generator_base.py
markdown_checker/reports/md_reports/__init__.py
markdown_checker/reports/md_reports/generator.py
markdown_checker/reports/md_reports/templates/paths/broken.md
markdown_checker/reports/md_reports/templates/paths/tracking.md
markdown_checker/reports/md_reports/templates/urls/broken.md
markdown_checker/reports/md_reports/templates/urls/locale.md
markdown_checker/reports/md_reports/templates/urls/tracking.md
markdown_checker/utils/__init__.py
markdown_checker/utils/extract_links.py
markdown_checker/utils/format_output.py
markdown_checker/utils/list_files.py
markdown_checker/utils/logging.py
markdown_checker/utils/spinner.py
markdown_checker-0.2.5.dist-info/licenses/LICENSE
markdown_checker-0.2.5.dist-info/METADATA
markdown_checker-0.2.5.dist-info/WHEEL
markdown_checker-0.2.5.dist-info/entry_points.txt
markdown_checker-0.2.5.dist-info/top_level.txt
markdown_checker-0.2.5.dist-info/RECORD
